mrqy/QC.py
mrqy/QC4d.py
mrqy/QCF.py
mrqy/__init__.py
mrqy-0.0.3.dist-info/LICENSE.txt
mrqy-0.0.3.dist-info/METADATA
mrqy-0.0.3.dist-info/WHEEL
mrqy-0.0.3.dist-info/top_level.txt
mrqy-0.0.3.dist-info/RECORD
