Metadata-Version: 2.1
Name: mrqy
Version: 0.0.3
Summary: MRQy is a quality assurance and checking tool for quantitative assessment of magnetic resonance imaging (MRI) data.
Author-email: Amir Reza Sadri <ars329@case.edu>, Mohsen Hariri <mohsen.hariri@case.edu>, Satish Viswanath <satish.viswanath@case.edu>
License: BSD 3-Clause Clear License
Keywords: MRI,CT
Classifier: Programming Language :: Python :: 3.8
Classifier: License :: OSI Approved :: BSD License
Classifier: Operating System :: OS Independent
Requires-Python: >=3.6
License-File: LICENSE.txt
Requires-Dist: numpy >=1.23.1
Requires-Dist: medpy >=0.4.0
Requires-Dist: matplotlib >=3.5.1
Requires-Dist: pydicom >=2.3.0
Requires-Dist: pandas >=1.4.2
Requires-Dist: scipy >=1.8.0
Requires-Dist: scikit-learn >=1.0.2
Requires-Dist: scikit-image >=0.19.2
Requires-Dist: umap-learn >=0.5.3
Requires-Dist: importlib-metadata ; python_version < "3.8"
